LogError/Code.py
LogError/__init__.py
LogError-1.0.2.dist-info/LICENSE
LogError-1.0.2.dist-info/METADATA
LogError-1.0.2.dist-info/WHEEL
LogError-1.0.2.dist-info/top_level.txt
LogError-1.0.2.dist-info/RECORD
