Metadata-Version: 2.1
Name: LogError
Version: 1.0.2
Summary: UNKNOWN TRACEBACKS!!!! Deal with them Carefully :-D
Home-page: https://github.com/v1s1t0r999/LogError
Author: v1s1t0r999
Author-email: aditya.funs.11@gmail.com
License: MIT
Platform: UNKNOWN
Classifier: License :: OSI Approved :: MIT License
Classifier: Programming Language :: Python :: 3
Classifier: Programming Language :: Python :: 3.7
Requires-Python: >=3.6
